simons/VERSION.txt
simons/__init__.py
simons-0.0.1.dist-info/LICENSE
simons-0.0.1.dist-info/METADATA
simons-0.0.1.dist-info/WHEEL
simons-0.0.1.dist-info/top_level.txt
simons-0.0.1.dist-info/RECORD
